pyPrivnote/__init__.py
pyPrivnote/constants.py
pyPrivnote/crypt.py
pyPrivnote/exceptions.py
pyPrivnote/model.py
pyPrivnote/util.py
pyPrivnote-0.0.1a1.dist-info/DESCRIPTION.rst
pyPrivnote-0.0.1a1.dist-info/METADATA
pyPrivnote-0.0.1a1.dist-info/RECORD
pyPrivnote-0.0.1a1.dist-info/WHEEL
pyPrivnote-0.0.1a1.dist-info/metadata.json
pyPrivnote-0.0.1a1.dist-info/top_level.txt
