Metadata-Version: 2.0
Name: pyPrivnote
Version: 0.0.1a1
Summary: A Python Interface to Privnote service
Home-page: http://pypi.python.org/pypi/pyPrivnote/
Author: Gleb Zaripov
Author-email: gleb-zaripov@yandex.ru
License: GPLv3+
Keywords: privnote priv note pyprivnote notes cryptography private message self-destroy self-destruct
Platform: UNKNOWN
Classifier: Development Status :: 3 - Alpha
Classifier: Intended Audience :: Customer Service
Classifier: Intended Audience :: Developers
Classifier: Intended Audience :: Other Audience
Classifier: Intended Audience :: Science/Research
Classifier: License :: OSI Approved :: GNU General Public License v3 or later (GPLv3+)
Classifier: Operating System :: Unix
Classifier: Operating System :: Microsoft :: Windows
Classifier: Operating System :: MacOS :: MacOS X
Classifier: Programming Language :: Python
Classifier: Programming Language :: Python :: 3
Classifier: Programming Language :: Python :: 3.2
Classifier: Programming Language :: Python :: 3.3
Classifier: Programming Language :: Python :: 3.4
Classifier: Topic :: Communications
Classifier: Topic :: Software Development :: Libraries
Classifier: Topic :: Software Development :: Build Tools
Classifier: Topic :: Software Development :: Version Control :: Git
Classifier: Topic :: Security :: Cryptography
Requires-Dist: pycryptodome
Requires-Dist: requests
